rpa_openapi/Enums.py
rpa_openapi/RPAClient.py
rpa_openapi/RPAException.py
rpa_openapi/Utils.py
rpa_openapi/__init__.py
rpa_openapi/V20200430/ApplyAppRequest.py
rpa_openapi/V20200430/ApproveRequest.py
rpa_openapi/V20200430/BaseQueryRequest.py
rpa_openapi/V20200430/CancelRequest.py
rpa_openapi/V20200430/CreateServiceTaskRequest.py
rpa_openapi/V20200430/CreateTaskScheduleRequest.py
rpa_openapi/V20200430/DeleteClientRequest.py
rpa_openapi/V20200430/DisconnectClientRequest.py
rpa_openapi/V20200430/QueryAppApplyRequest.py
rpa_openapi/V20200430/QueryApplyListRequest.py
rpa_openapi/V20200430/QueryAppsRequest.py
rpa_openapi/V20200430/QueryClientByUuidRequest.py
rpa_openapi/V20200430/QueryClientViewByIdRequest.py
rpa_openapi/V20200430/QueryClientViewsRequest.py
rpa_openapi/V20200430/QueryMemberClientViewsRequest.py
rpa_openapi/V20200430/QueryMyAppApplysRequest.py
rpa_openapi/V20200430/QueryMyAppsRequest.py
rpa_openapi/V20200430/QueryServiceResultRequest.py
rpa_openapi/V20200430/QueryTaskBatchByTaskScheduleIdRequest.py
rpa_openapi/V20200430/QueryTaskByClientIdAndStatusRequest.py
rpa_openapi/V20200430/QueryTaskByClientIdRequest.py
rpa_openapi/V20200430/QueryTaskByTaskBatchIdRequest.py
rpa_openapi/V20200430/QueryTaskLogsRequest.py
rpa_openapi/V20200430/QueryTaskScheduleByClientIdRequest.py
rpa_openapi/V20200430/QueryTaskSchedulesRequest.py
rpa_openapi/V20200430/QueryTaskStatusRequest.py
rpa_openapi/V20200430/RejectRequest.py
rpa_openapi/V20200430/Request.py
rpa_openapi/V20200430/ResponseModels.py
rpa_openapi/V20200430/TerminalTaskRequest.py
rpa_openapi/V20200430/UpdateClientDispatchModeRequest.py
rpa_openapi/V20200430/UpdateClientInfoRequest.py
rpa_openapi/V20200430/UpdateClientStatusRequest.py
rpa_openapi/V20200430/UploadFileRequest.py
rpa_openapi/V20200430/__init__.py
rpa_openapi/V20200430/path.py
rpa_openapi-1.0.1.dist-info/LICENSE
rpa_openapi-1.0.1.dist-info/METADATA
rpa_openapi-1.0.1.dist-info/WHEEL
rpa_openapi-1.0.1.dist-info/top_level.txt
rpa_openapi-1.0.1.dist-info/RECORD
