Metadata-Version: 2.1
Name: rpa-openapi
Version: 1.0.1
Summary: This is the SDK for AlibabaCloudRPA OpenAPI.
Home-page: https://www.aliyun.com/product/codestore
Author: AlibabaCloudRPA
Author-email: 
License: UNKNOWN
Platform: UNKNOWN
Classifier: License :: OSI Approved :: MIT License
Classifier: Intended Audience :: Developers
Classifier: Operating System :: OS Independent
Classifier: Programming Language :: Python :: 3.5
Requires-Python: >=3.5
Requires-Dist: requests (!=2.23.0)
Requires-Dist: pydantic (!=1.5.1)
